slixfeed/__init__.py
slixfeed/config.py
slixfeed/py.typed
slixfeed/syndication.py
slixfeed/version.py
slixfeed/__pycache__/__init__.cpython-314.pyc
slixfeed/__pycache__/version.cpython-314.pyc
slixfeed/configuration/directory.py
slixfeed/configuration/focuscript.py
slixfeed/configuration/profile.py
slixfeed/configuration/settings.py
slixfeed/configuration/singleton.py
slixfeed/data/configs/accounts.toml
slixfeed/data/configs/filters.toml
slixfeed/data/configs/filters.txt
slixfeed/data/configs/lists.toml
slixfeed/data/configs/operators.toml
slixfeed/data/configs/queries.toml
slixfeed/data/configs/selectors.toml
slixfeed/data/configs/settings.toml
slixfeed/data/css/stylesheet.css
slixfeed/data/focuscript/atom-0.3.focus
slixfeed/data/focuscript/atom-1.0-reverse.focus
slixfeed/data/focuscript/atomsub-1.0.focus
slixfeed/data/focuscript/gemtext-1.0.focus
slixfeed/data/focuscript/json-1.0.focus
slixfeed/data/focuscript/json-1.1.focus
slixfeed/data/focuscript/microformats-2.0-xhtml.focus
slixfeed/data/focuscript/rss-2.0-extended.focus
slixfeed/data/focuscript/rss-2.0-podcast.focus
slixfeed/data/focuscript/rss-2.0.focus
slixfeed/data/focuscript/twtxt-1.0.focus
slixfeed/data/graphics/image.svg
slixfeed/data/graphics/image.svg.license
slixfeed/data/graphics/image_black.svg
slixfeed/data/graphics/image_black.svg.license
slixfeed/data/graphics/image_semi_transparent.svg
slixfeed/data/graphics/image_semi_transparent.svg.license
slixfeed/data/graphics/image_transparent.svg
slixfeed/data/graphics/image_transparent.svg.license
slixfeed/data/graphics/image_white.svg
slixfeed/data/graphics/image_white.svg.license
slixfeed/data/info/about.toml
slixfeed/data/info/commands.toml
slixfeed/data/info/feeds.toml
slixfeed/data/info/information.toml
slixfeed/data/info/profile.vcf
slixfeed/data/xslt/atom.xsl
slixfeed/data/xslt/atom_as_xhtml.xsl
slixfeed/data/xslt/extract-filename.xsl
slixfeed/data/xslt/metadata.xsl
slixfeed/data/xslt/opml.xsl
slixfeed/data/xslt/opml_as_xhtml.xsl
slixfeed-2025.12.31.dist-info/METADATA
slixfeed-2025.12.31.dist-info/WHEEL
slixfeed-2025.12.31.dist-info/entry_points.txt
slixfeed-2025.12.31.dist-info/top_level.txt
slixfeed-2025.12.31.dist-info/RECORD
