Metadata-Version: 2.4
Name: Slixfeed
Version: 2025.12.31
Summary: News aggregation service for XMPP.
Author-email: Schimon Zachary <sch@fedora.email>
License: MIT
Project-URL: Homepage, https://schapps.woodpeckersnest.eu/slixfeed/
Project-URL: Issues, https://git.xmpp-it.net/sch/Slixfeed/issues
Project-URL: Repository, https://git.xmpp-it.net/sch/Slixfeed
Keywords: activitypub,activitystream,atom,atomsub,bot,chat,deltachat,email,foaf,focus,gemini,im,jabber,json,news,pubsub,rdf,rss,service,syndication,twtxt,xml,xmpp
Platform: any
Classifier: Intended Audience :: End Users/Desktop
Classifier: Natural Language :: English
Classifier: Programming Language :: Python
Classifier: Programming Language :: Python :: 3.10
Classifier: Topic :: Communications :: Chat
Classifier: Topic :: Internet :: WWW/HTTP :: Dynamic Content :: News/Diary
Classifier: Topic :: Internet :: XMPP
Classifier: Topic :: Office/Business :: News/Diary
Requires-Dist: Agunua
Requires-Dist: aiofiles
Requires-Dist: aiohttp
Requires-Dist: bleach
Requires-Dist: chardet
Requires-Dist: deltabot-cli
Requires-Dist: jetforce
Requires-Dist: lxml
Requires-Dist: markdown
Requires-Dist: python-dateutil
Requires-Dist: pythonvCard4
Requires-Dist: readability-lxml
Requires-Dist: reportlab
Requires-Dist: slixmpp
Requires-Dist: tomli
Requires-Dist: tomli_w
Provides-Extra: omemo
Requires-Dist: slixmpp-omemo; extra == "omemo"
Provides-Extra: proxy
Requires-Dist: pysocks; extra == "proxy"
